libnumerixpy/__init__.py
libnumerixpy/math/__init__.py
libnumerixpy/__main__.py
libnumerixpy/base.cpython-313-x86_64-linux-gnu.so
libnumerixpy/math/basemath.cpython-313-x86_64-linux-gnu.so
libnumerixpy-0.1.2.dist-info/LICENSE
libnumerixpy-0.1.2.dist-info/METADATA
libnumerixpy-0.1.2.dist-info/WHEEL
libnumerixpy-0.1.2.dist-info/RECORD
